{ "compressionlevel":-1,
 "height":84,
 "infinite":false,
 "layers":[
        {
         "compression":"zlib",
         "data":"eJzt3ctu1DAUAND8\/0fQCzso3UGX0CnlL3h0Stmw4hMIUiIFK5k8GpyJe450lYzt8b3TRaV4LE9VAQAAAAAAAACUI+q4quNtE1dNxML5XtfxZo3C2LWY2Q5TxED7i5xFUJzYugCKFFsXQJEuty4AAJ6Zu60LoEiPWxcAAAAAFC2qdfdujc31ro73dVwvnL99\/1BMnTeSua6btovq6d\/dTvl7PjXHuYutC9hInGjr68uRf8yntYsYsMb\/mef6\/XecaOvry5F\/zI+1i2B10dN2eaIvR372Lxb25cjPfsXCvhz52a9Y2JcjP\/t1caIvMuTPkYPzEoXk4LzkWHuJDDn63NZxmDh2aFy7jnY7M\/ehmrcGl+a\/GannQx0fJ86VSj9LrrXCtUXGXK869w91HEfGtPrG\/dWuoz3MrONYDa\/B\/Z6Q\/36knm91fG\/uX47MlUo\/y17XCmPrAihSbF0ARXJeAgA5fO7cH5Jrqu+5ea\/Pm\/xfPzv3x+SaPlt3nzXbvr0+bwIAAAAAAAAAAAD\/7k+115S1dPen2msKAAAAQAl+bV0AAMWa+xtC6W98AQDQb+gM+5vmOmWvVDrmbqCv7zzA9L1Tz+bnvA2dYX\/fXPv2Sn2p42vndTrmcaCv7wz69L1j59QD7MEfD8V1Hg==",
         "encoding":"base64",
         "height":84,
         "id":1,
         "name":"Decorations",
         "opacity":1,
         "type":"tilelayer",
         "visible":true,
         "width":150,
         "x":0,
         "y":0
        }, 
        {
         "draworder":"topdown",
         "id":2,
         "name":"Powerups",
         "objects":[],
         "opacity":1,
         "type":"objectgroup",
         "visible":true,
         "x":0,
         "y":0
        }, 
        {
         "draworder":"topdown",
         "id":3,
         "name":"Enemies",
         "objects":[
                {
                 "gid":253,
                 "height":16,
                 "id":39,
                 "name":"",
                 "rotation":0,
                 "type":"",
                 "visible":true,
                 "width":16,
                 "x":1128,
                 "y":656
                }, 
                {
                 "gid":253,
                 "height":16,
                 "id":41,
                 "name":"",
                 "rotation":0,
                 "type":"",
                 "visible":true,
                 "width":16,
                 "x":760,
                 "y":336
                }, 
                {
                 "gid":253,
                 "height":16,
                 "id":42,
                 "name":"",
                 "rotation":0,
                 "type":"",
                 "visible":true,
                 "width":16,
                 "x":600,
                 "y":336
                }, 
                {
                 "gid":253,
                 "height":16,
                 "id":43,
                 "name":"",
                 "rotation":0,
                 "type":"",
                 "visible":true,
                 "width":16,
                 "x":352,
                 "y":336
                }, 
                {
                 "gid":253,
                 "height":16,
                 "id":44,
                 "name":"",
                 "rotation":0,
                 "type":"",
                 "visible":true,
                 "width":16,
                 "x":24,
                 "y":272
                }, 
                {
                 "gid":252,
                 "height":16,
                 "id":52,
                 "name":"",
                 "rotation":0,
                 "type":"",
                 "visible":true,
                 "width":16,
                 "x":1072,
                 "y":576
                }, 
                {
                 "gid":254,
                 "height":40,
                 "id":54,
                 "name":"",
                 "rotation":0,
                 "type":"",
                 "visible":true,
                 "width":32,
                 "x":928,
                 "y":384
                }, 
                {
                 "gid":254,
                 "height":40,
                 "id":55,
                 "name":"",
                 "rotation":0,
                 "type":"",
                 "visible":true,
                 "width":32,
                 "x":248,
                 "y":192
                }],
         "opacity":1,
         "type":"objectgroup",
         "visible":true,
         "x":0,
         "y":0
        }, 
        {
         "draworder":"topdown",
         "id":4,
         "name":"player",
         "objects":[
                {
                 "height":8,
                 "id":2,
                 "name":"",
                 "rotation":0,
                 "type":"",
                 "visible":true,
                 "width":8,
                 "x":-8,
                 "y":0
                }],
         "opacity":1,
         "type":"objectgroup",
         "visible":true,
         "x":0,
         "y":0
        }, 
        {
         "draworder":"topdown",
         "id":5,
         "name":"Special Blocks",
         "objects":[
                {
                 "gid":270,
                 "height":64,
                 "id":14,
                 "name":"",
                 "properties":[
                        {
                         "name":"dest",
                         "type":"string",
                         "value":"26.json"
                        }],
                 "rotation":0,
                 "type":"",
                 "visible":true,
                 "width":8,
                 "x":800,
                 "y":664
                }, 
                {
                 "gid":271,
                 "height":64,
                 "id":15,
                 "name":"",
                 "properties":[
                        {
                         "name":"dest",
                         "type":"string",
                         "value":"24.json"
                        }],
                 "rotation":0,
                 "type":"",
                 "visible":true,
                 "width":8,
                 "x":392,
                 "y":200
                }],
         "opacity":1,
         "type":"objectgroup",
         "visible":true,
         "x":0,
         "y":0
        }, 
        {
         "compression":"zlib",
         "data":"eJztwTEBAAAAwqD1T20KP6AAAAAAAAAAAAAAAAAAAAAAAAAAAAAAAAAAAAAAAAAAAAAAAAAAAAAAAAAAAAAAAACAlwHE4AAB",
         "encoding":"base64",
         "height":84,
         "id":6,
         "name":"fake_tile",
         "opacity":1,
         "type":"tilelayer",
         "visible":true,
         "width":150,
         "x":0,
         "y":0
        }, 
        {
         "compression":"zlib",
         "data":"eJzt3WmOHElyBWDPpdm5SJpLSAcYAQK0\/OyNS5Oa0Q2kmRvoYLqiKqB44BePUVxUWSyyEA4EMjPSwxdzs2fPzD2rzmOM4911vrv28+thfn+c31\/urtP8+TTfO851pu92873r\/N7n0vZuvk7z51N9v6fPvD9Xm5f5utbnffXvWHe05div1NvX57SdsR7ndjKP6\/xM6h+QWebtvT3jcG572sq4I4P0Gxm5Nmf6tt3L\/N15LNdGWZ9KpplP5naY6yg77x\/Gh3JqmR14PvLZU8e++vmszQGZZ3yZuzK6jqW+XWlPHcq48l5dy\/iUqWM50W9kmbbO1Ms40v51LOV54vl93TtQ91L9umapuxvL8WQckXvG7zyUybnuZd5H+sqYMt7oyrX6vFQ99d85ihln5pkxpn7GlvVuHY2+O\/7IQfnux1Lv97SftqJHF\/pTn8STyEZcSv3okTbZmNJ4cB1L\/VNXW8fUJ+fUOBE7WZOH+iquXbmX9Y3s\/C7tnFfqqmNrGKnOZ1xX+ogs99TLeE9jqQOpJxY5ZvF2N5Z64Foon0v11zhwGcu1dQ0jc31B1k6di97r6yIDsek6PtSjY71vP6gPVD76GmWjT1WPxaLLWGJ449qxnskcbXdXfe\/H0vZtN2245u2D266CU7t6Rp933zq4Hq6ZPjbzPPN91t1xK4s1\/BCvxUH9gH2c67nUF0t39Yx6eR5L\/RdLo+\/q6o5Lefp95my\/x7Fcp+hv66O223i341l1yXXf1f3zWOqGzx5X+stapa2s86GeV2fTX2Ni45n4v+NzdEyu1TzENfF5ff5h5fK5Y9Xr9bmOpY6I0ZFLbCF4JG92PvL4zF1bkntf6EeZtlybJxpfXGmv5X2sfsWa1sPm+vbdOtmc1TnnmctY4seOftsm9J27scRCde5c\/Tf3aD4sxne8piwjz+ZxrrM4JXfTF13GUs6t02KYei5nFGuyPtd6Rpzd17P6Fn1I8xq5ojxTfYkc5bKtE+LLlf7kWLvqo\/2zYzE2WeO4zVcbm5p7NWcxBpCnq2etU84tYzPeVIb60sjTMYoxyqZ5T8tV3XC+xmBytn09qw891XfG8uptx\/iN5eJU5tC+S\/ka\/6Yd9bx9kfkL11B8kB8oy2M917is\/bVP0vZbBnJQfVivR7DmTL\/qq3GJ+tPYqR02vrtm2mrnEJStPF4Mlp+bz0gd59jrJSZ3zJOruYb8Wp2VQ2UsFz7LAdQrOaD2l7rarWvQ8aCfm78fxnINWpdzKefWCXUzn+Wk4seh6omTYpAyigyyLp1nUNf0SfqpS7Xdvlo7yhj73pk+5FHKtfnAub6TCxiTncfSDo1B1JXmJ8ZgvT5y147TjU3k9M7TWOdQfba+7MdSZ9QRxyUPbz7uerfv817zRTmp+K+vMj7oMTgnsUTfIV8+VJ3GQ219Tx+Radtl40bk1PPIXOw3cztQRz6ljxQ71uK8vHas2tytsexczxqzaXNi7Ym6eU4utMb5nLOcLTanDbje6qe4rKyU+6naOI2lPYh7aeNUbV\/pV3+nnI3jmtcZR6l7+gZtvzHsVPU7TyFGKKvOJehL5WzNYbUh\/ZHfp0+xt2Pm5kXyXnmanLjtM3NoXNLuj+ND224e1D5VfHOe+jj5jXJSn5W38arYmeflf81ptHPtZg0TfVXO93G21hF9g5imDjY\/d23lSPrRNf1VX9XLjunkxWJC3vvZuDL9nlbaMmaJPV\/Hcv31HfpYeUJzG\/WyubXj8Dnb6Tilx5U68ld9rPPU\/2Q84plYrJ019skH5LlrsbLr9ma+fr+73s3X9PntfL2b6\/V3b+bPv8+Xz7yd772t795w3\/Z+5zXXmffveHWsLXNjho6jzQlEbuJi5Kyvlv8o\/45x9BexL3UjcpcLiyW7qid2B9fEmguf84w6Zkyi35VDXOn3OpZ2lrE3N2+O6hjkAv8+Pq\/8zWfWu2X5nD5\/GUs5yaX0yR13KQ\/jEHGk41PtUVxqvyR+iRPmHtLGZeW5Ne5hvqPnmnVuH5w5NEeW74tFHSPsxtKujCmVcfv16f2fP7Zo33j5w1jGGa63OqEd6jujb52\/6vjssnK\/+YLr75rrW9TNQ7Xf8Yzz6VgwY3Xeh7HUsW7POMqYQj8rHlvfuCh+8DKW8+q48T8+sm7fQ\/l1vJdp7DJ64tpE5mJ4Y7t6ZXygvPQpcih5sX03XjQutL9Ov\/q7tRyN4xdfmjs112z5GB+u5SKcs3Gw+mqMmuf+9LFF+8bL\/8yv\/71d39Q16df3jldb+fZKsPnvnnogW3lW5Tnwq618e2XiV5tebeXWZcOrrTxG+R7jwX986gFs5ZNl4uxfC6\/++e76+7vrH+6uf5mvL\/2cvbEf764f5msqTx1Xb9eHeYavkW+fdGrSi3+9u\/5tvNeTL\/1szs99C\/Pe5u\/MSXru4FTfHbjvs+lj7RxK7x25v5\/v3Ocx39j7eJ6VMTfrfoDzcg\/GvRlzu54bcT69P+E+uHtIa\/l09zHcv+l8\/dfg7bfAqXz2DE\/riXLwjECfr1o7k+CZkT3PmCffV799Vs68tfl\/z0J4\/iP33Ht0rL1P5F5m58zdSzDn7dkoz2h4BsQ9AfefPBOhbq+d2Uo9z449Jr+6FU7lc\/Skz5y57u4xK+c+2+FZoyvfq7eeK3HP1+fFI\/dl1a\/DSruu\/Z767ktrJ86v9wOvfNfnWNynis4ou9iCuL2rOp7j8zyP++c+O73\/3PMMX1puiVP57Jkx96YiR31H61Tbeu\/BiSfui4k5Ykr66n3kPpfk2av2r\/rifbVrf42DnvXxPESfN1CfIq8+z9D247kidUhZakOeJRTrH0Ovbo1T+RxZ5kyW58NyFmztfFiu01ie3\/IMWOp7psz37+g79a5j\/YyZdXz\/hr6m61z1343luDLetTNutt2yUA4937crMnSM1ve+9U7cc3zxj7fSq1vj0sc+\/9MDxvm3D3h27flbt\/el3z9Wv58q952L+2m8x89b6NWtcem+zw\/Rqa08fpn0KnHM95YX3cq3W6azu+Gq9+HVltfeypeWCa88D\/n67np5d\/3G+wnLfpzv\/efTDHMr31n5eSzjc8+hGkuaF\/7rk4x0K99LmX5r4J6AuVjP\/ne+dnq\/6dZWPlbyW4Poi3sA5qzNpeX7vzzBeLfyfZSJX\/V+gHlkfzfmb+Cig5tubWWtTPGgewTurfbvy9x3EM82n7iVLhNe6dvc2\/E3iHL4YJfcfsOtrVgmfuXvZT2nE13zTI77uu5PTvfXchB\/nF\/vy4HdIjf20Db++OkqD6p\/6+e\/hzLhVfTKnIJnc8So\/jsE6tz0\/sX4v1zXdO+H+fU1n1\/M1w88O9V\/xZX82cv5c77\/bb5ezW3k9TLenxn9cb5ez98nB+e50lwv5ytjfEH9H3j+t\/n5F\/SXviOrzDVt\/kab6fvH+bvT\/JrvX86v6ec5\/M4g+av+OynBIn+fHR3zt96eDXIPW752qPqeIcoznitrXPSsUXDU86FpI+Ny7J6H8bxTzsV4fsozqLbhOZI+W+L8PC\/a5wU929c2eRpL7H8ueuU5UmO9PmcZPm8OVXmtnVdrf9rnGD2f5zp5jij6Yx7N80F5xjNT\/p2NtXNv5lb6fJ1nTs\/04Ri1P8\/3eubXv7GwX+nHe9rF9\/z3V1Imveq\/T9HnnP07Gp6jNr\/V56TPK214Js7z2cr9QLtX+hYPd\/Tbz3pm3POdwYU+Y+f5cfGx\/3ZG9Mwzz+aSvd\/n+vrvbTg\/z5Gm7nPY\/594u3YqPotNnoc91dXnVLVb8Srr3X8DxTP4\/ZsCcfJU\/USnxC\/PCXuO0v4vtKHui4F9fr3P1qZPz97qz90b8xzmsfrr31RMr88Br5Jn6PPu0RdtrdddPuN711+5xt7lSP6uIc8bL3Sc2pii77xWH\/4G4ULbxrPRbfmaczhWO\/Ko+863r\/3uIW2L5dfqM+P7GF59Kvb9Vs6eTHglbww+Nyb1WX5l0ufl209mXeXgzd2ay7rmeVbc0d+Ja+2T5C3NGfd19Xf6Ru3ntPKM8Ub61Da0Q\/UqbV2r38TCU8yYsySv5nq5Z4ycePsyf+cZ\/dN4HyP\/1\/g6JedF9Tv6KjmzttzxmH7GvKn8RT8THZT\/+3sBeYu+rHFK7nRc6SvjO\/K58yiNocYMcvhdPW+M4NiNH52\/vKJjY3mIvwURV8XZ3vfwdwp9NqXH9jXOOv08llzbNewYTD3q326knr8VOVDfV\/labFcsWYsZzWEcacP9SrmQ6+L6+6pfM05QDs7Teci5so4ZgzLIdy0DczX6zbX4wLnJF\/S58n79RHPFtP\/YuuV50Ywzssg6537Wx7mv4XjzksSB5gWaw9uXPlfcjPxcK2NNcdV4X7\/eeQN5njys97Z6npmXMan613GOe63qv3oi1xM\/va8dqnftc+WtnaeLvB\/TJ+acjPxH3DbuEa+NjcTbztWscezO8Rjze894rjHANcn6Gw+6rpGj\/F5enXVXz40Z0qd637Yg18xY7E\/\/qo7q19rXKxvt2HxZY7m8V72Ta5rb\/ct4nJK\/TS1nkp8qk\/Zh4n5zBrGmcb\/5hlxWjiueK6vcy5qt2bI5r8YVX+WHYmLHAWKWuKWvPPG8+mVM3TGA9rKnjfu4nzotLzdHZE6kc3jaadboMXxi+FXHV52TcU2z5uJq8yHtomPEzp3KJyJX7bX52xo2dT9pU73LlbnI8zMuOb3+WkzstRTrxFux6kJ9uUHj3XEs9bHtqO3fPGHHPaf63r7Eyun+X8dtS\/IMzl\/c0GbEB32iPlu\/Iq\/Q70d39Hfi1X15HrmHbR3HUieMsfR\/wRZjD\/XBHFWe6zhRbJRL6sPMYXjPNe04Me+Nk5uba5fKVx6hHipj7VQOql8K37pFDuzXko06JJZm3fQjazmB5ocZsxgo51Gn9S2X6qexXD+hnORvrveettU1ee256om9+kTXX34sRspvmrNeqw\/t81Btt1\/Xh7RdGFfv6hnri33d15Tneujvk\/8w3tuScZKcQ+zNemR88nPtWy6iTalbcg7X33maU+g8h+toHGZM4ZjEozOv+mB5kbbf9czFiEvaivptn3K+5ufisbLN+LXdNV3T5tZwMOPW7vTRWZdb7CP9THvtm5oHqjd+Z25CbFIOqdPxe+eR1tZLfhpZ+EzzQrG+\/aL8t\/2F+rFf6af9j\/NZwxFjlcv4UGbak3kOYyX1\/VBtt09u29COMmd9ass7929xTifn2\/V56oNz7NyPuRnx25jcdnZjKc\/mPPdxzc4FdIyhziqf5vFX+hAr5bTal\/xIXHZt5IL6ZjGi8y+ORduRazYXz3PKV9lcqat\/6fXrGEscyftb6JXnkI1FMmZ5fMfL+qTIwBzUsdpq3iUm6y\/ll+YzTmNpk5GfdeXcYpS5HPUobahfa\/5XzJK7nOs7uaZylQOtxaq7+k5+or5mTsqo\/Znj6hi4Mbq55lT3Fn\/\/JedkHOOZS5kZW3QORD6qPspfOz8jzzSWby6s\/alDzfO0d2NM\/a227bgOPOdYGw+N7xqjtb9jvRcfMl\/HL3\/1VVvXh2uH2mb7CvMg6mzqr2H9pFcP\/b8jv9Bfx18ZT2SjLcix5Yna534s59T2kvVrvJSPG481P22bFzejM37WR4p5Yq0YKF6oI8Y26mPrtj7OsbW+d7wj3p5pVy4gXxJzvOeaKqeOf\/Wpt\/KDP9G\/9iZ2ygMy36xp7EKbkROIXf1c7nd+r+Nv9VjMM27Vr+rHxBHbyzj39Zz63ViiXMRW5yIWiVPmsOLPmuu43tqretljF987ju\/3mWvmElnLTaa6t\/CDwavGYtflWK\/6YrmvuRHtVE7e8VvsUB8r1zHnYJ5C\/DR+k+Mq8x3tGr+nbb\/PPTGlfYzczfriYvTEvNR+LOccbBe\/r7R9GEv9z7NiatpQR7Q1ZaYflq\/LYW6RZ8i+s9wlYxUDxAXtqjFjt\/KMdqacOybUP8qNmxe41tE1fV77vqyfl+urnja+NYZ0zkD+1Pxbn33hcl7NCcV7uaUxqTjX\/lL9E5fkJK13GW9k+jG9+txc\/C9jab\/NY7UFfZ38Xl1awwr5h3G\/WK5Mbc8Y3jWWz7a\/kN91jqDjW+3bmNy1NM7VT7uG6pMxa\/pyXOZVlGfHAeq4XOQ+Dr\/WV+Qibl9WPssFptdX4\/1vIV+P97\/HzHefKr+OJS5qX53XMw6Wf7Yf9L1cSX040Z6xuXmaNf5szqDjBNdVPmrb4o5xQGy6fVbjTWzCOQVbO28gt9nRdut8+8zmRfK1jEW5id1y2uayYrQ+V3xN3Tdj+beT38zP5W8hf6r8Mpa2K7ZHRo7dNWp8VZfEhuNY2r5xp\/qzhvtt0+r0rvqVA2vbGeNaLCff8P2aDcj5rtwTYzvWkAO41vJwY+D26\/pDub7xzm7cjwWOx\/HL\/Tu+vM8PfsnfTk6+Xd2VKzYfVH7y7kvd71habq397au\/5j+RuTIQX3cr9fRju\/GhPhvvu1b6JnHFccmxUldscb2P1f91pT3H3+MTI8W32Ll+VXmfuYwRMgbnmLb87lbxoGOXt+j3jJP2Y10m2ov+y5hN25aLNI881PeORV+jbp6p235Bf6jOaEvGEqdqz9hPXqePaywyP2Ecp39ybfOsGJ5+9SPqs1xMn72jHfG1uYU5iozrFvFg\/GDHKPrAjFfMiKwbi+Uixood98ql\/c7cRsc3Yl\/sUf1X1q3z6U9MdS31ex1LmUuRo7cvtn0\/y13k2tqysam5Bjmbfrx5nj6h9di1UrddW9ue9Oqh+fbkGcQo56dPa9yIDhi3qDeZgzqgbcqV2gfqH1tvjWk6H9RjU+7GUdq5PCpjMb6Ud7km17HE347TOq6MHood6ru8yFyPmKYd6ks6Pm4dvtJHY7f2cis\/+BPyE5vlFu0XDtzzmeahytoYTMxrPirv0HblLWKM49Y\/qMs+3zZ\/oH95jP5IHVTXduPD+YtNciVzYNqmnNxxi0EZuzkKdbxtQp6oHjVWihXK\/aF+cPr7XskziAHGLhmPfuNY3+W1OYTycs2as+l\/2gd3nHaizp4+rGc+puOHxonOBciVOidgP+rnuZ6VO7Zfl\/u3DLTBjjdaf23jWH0pX9ei4zJ9pzHrQ\/Dqp7GM6Z\/6\/7Vu1\/KaSv+Prjfjw\/9Zlv8v9rbqnvgur+ex\/r\/FkpPyf4T9f8vPY4nNW3leZe3\/bD3W\/wSzJL8QjNzKVm5RJj8ov9zKVh5a\/P8l4Wpb2cotirz9+sRj2crzKdGrYNZWnme59d\/v+1R70atwrKeOq7frwzzD6\/H+b7q\/nN+\/4PUVn19S\/yXPTLjh38p\/sdJGns3rq6rzmrrnsX42K+Mzd+y+nWczPD\/iHoX7Zb2vY27dvTn3OLuN3o+xXXOxa\/u9fQ7HvcsD7XZe2jMA5n0dn3vH5sLN35sT73MDva\/sPsraPpP7O50\/d7\/T\/VWfV2bmfn3OfTbHlByreWT3ylrezsWzEOk3eej\/Bfez804=",
         "encoding":"base64",
         "height":84,
         "id":7,
         "name":"Tile Layer 1",
         "opacity":1,
         "type":"tilelayer",
         "visible":true,
         "width":150,
         "x":0,
         "y":0
        }, 
        {
         "color":"#000000",
         "draworder":"topdown",
         "id":8,
         "name":"solid",
         "objects":[
                {
                 "height":112,
                 "id":16,
                 "name":"",
                 "rotation":0,
                 "type":"",
                 "visible":true,
                 "width":400,
                 "x":0,
                 "y":0
                }, 
                {
                 "height":32,
                 "id":17,
                 "name":"",
                 "rotation":0,
                 "type":"",
                 "visible":true,
                 "width":8,
                 "x":392,
                 "y":112
                }, 
                {
                 "height":48,
                 "id":18,
                 "name":"",
                 "rotation":0,
                 "type":"",
                 "visible":true,
                 "width":976,
                 "x":224,
                 "y":192
                }, 
                {
                 "height":16,
                 "id":19,
                 "name":"",
                 "rotation":0,
                 "type":"",
                 "visible":true,
                 "width":208,
                 "x":144,
                 "y":240
                }, 
                {
                 "height":160,
                 "id":20,
                 "name":"",
                 "rotation":0,
                 "type":"",
                 "visible":true,
                 "width":16,
                 "x":0,
                 "y":112
                }, 
                {
                 "height":64,
                 "id":21,
                 "name":"",
                 "rotation":0,
                 "type":"",
                 "visible":true,
                 "width":80,
                 "x":0,
                 "y":272
                }, 
                {
                 "height":48,
                 "id":22,
                 "name":"",
                 "rotation":0,
                 "type":"",
                 "visible":true,
                 "width":800,
                 "x":0,
                 "y":336
                }, 
                {
                 "height":64,
                 "id":23,
                 "name":"",
                 "rotation":0,
                 "type":"",
                 "visible":true,
                 "width":976,
                 "x":0,
                 "y":384
                }, 
                {
                 "height":160,
                 "id":24,
                 "name":"",
                 "rotation":0,
                 "type":"",
                 "visible":true,
                 "width":256,
                 "x":800,
                 "y":448
                }, 
                {
                 "height":16,
                 "id":25,
                 "name":"",
                 "rotation":0,
                 "type":"",
                 "visible":true,
                 "width":64,
                 "x":1056,
                 "y":528
                }, 
                {
                 "height":16,
                 "id":26,
                 "name":"",
                 "rotation":0,
                 "type":"",
                 "visible":true,
                 "width":400,
                 "x":800,
                 "y":656
                }, 
                {
                 "height":64,
                 "id":27,
                 "name":"",
                 "rotation":0,
                 "type":"",
                 "visible":true,
                 "width":32,
                 "x":1168,
                 "y":592
                }, 
                {
                 "height":352,
                 "id":28,
                 "name":"",
                 "rotation":0,
                 "type":"",
                 "visible":true,
                 "width":16,
                 "x":1184,
                 "y":240
                }],
         "opacity":1,
         "type":"objectgroup",
         "visible":true,
         "x":0,
         "y":0
        }, 
        {
         "draworder":"topdown",
         "id":9,
         "name":"Collision Objects",
         "objects":[
                {
                 "height":64,
                 "id":29,
                 "name":"",
                 "rotation":0,
                 "type":"slope_topright",
                 "visible":true,
                 "width":64,
                 "x":976,
                 "y":384
                }, 
                {
                 "height":64,
                 "id":30,
                 "name":"",
                 "rotation":0,
                 "type":"slope_topright",
                 "visible":true,
                 "width":64,
                 "x":80,
                 "y":272
                }, 
                {
                 "height":16,
                 "id":34,
                 "name":"",
                 "rotation":0,
                 "type":"slope_bottomright",
                 "visible":true,
                 "width":16,
                 "x":352,
                 "y":240
                }, 
                {
                 "height":48,
                 "id":35,
                 "name":"",
                 "rotation":0,
                 "type":"slope_topleft",
                 "visible":true,
                 "width":48,
                 "x":176,
                 "y":192
                }],
         "opacity":1,
         "type":"objectgroup",
         "visible":true,
         "x":0,
         "y":0
        }, 
        {
         "draworder":"topdown",
         "id":10,
         "name":"Camera Guides",
         "objects":[
                {
                 "height":224,
                 "id":36,
                 "name":"",
                 "rotation":0,
                 "type":"camera_y_guide",
                 "visible":true,
                 "width":672,
                 "x":224,
                 "y":224
                }, 
                {
                 "height":224,
                 "id":37,
                 "name":"",
                 "rotation":0,
                 "type":"camera_x_guide",
                 "visible":true,
                 "width":400,
                 "x":800,
                 "y":448
                }, 
                {
                 "height":240,
                 "id":38,
                 "name":"",
                 "rotation":0,
                 "type":"camera_x_guide",
                 "visible":true,
                 "width":400,
                 "x":0,
                 "y":0
                }, 
                {
                 "height":336,
                 "id":53,
                 "name":"",
                 "rotation":0,
                 "type":"camera_x_guide",
                 "visible":true,
                 "width":192,
                 "x":0,
                 "y":0
                }],
         "opacity":1,
         "type":"objectgroup",
         "visible":true,
         "x":0,
         "y":0
        }, 
        {
         "draworder":"topdown",
         "id":11,
         "name":"Map Hints",
         "objects":[
                {
                 "height":8,
                 "id":31,
                 "name":"",
                 "rotation":0,
                 "type":"map_wall_bottom",
                 "visible":true,
                 "width":800,
                 "x":0,
                 "y":440
                }, 
                {
                 "height":8,
                 "id":32,
                 "name":"",
                 "rotation":0,
                 "type":"map_wall_top",
                 "visible":true,
                 "width":800,
                 "x":400,
                 "y":224
                }, 
                {
                 "height":224,
                 "id":10,
                 "name":"",
                 "rotation":0,
                 "type":"map_ignore_region",
                 "visible":true,
                 "width":800,
                 "x":0,
                 "y":448
                }, 
                {
                 "height":224,
                 "id":13,
                 "name":"",
                 "rotation":0,
                 "type":"map_ignore_region",
                 "visible":true,
                 "width":800,
                 "x":400,
                 "y":0
                }],
         "opacity":1,
         "type":"objectgroup",
         "visible":true,
         "x":0,
         "y":0
        }],
 "nextlayerid":12,
 "nextobjectid":56,
 "orientation":"orthogonal",
 "properties":[
        {
         "name":"bgname",
         "type":"string",
         "value":"iridia"
        }, 
        {
         "name":"music",
         "type":"string",
         "value":"late_night_runaway.ogg"
        }],
 "renderorder":"right-down",
 "tiledversion":"1.3.4",
 "tileheight":8,
 "tilesets":[
        {
         "firstgid":1,
         "source":"..\/tilesets\/main_blue.json"
        }, 
        {
         "firstgid":111,
         "source":"..\/tilesets\/extras.json"
        }, 
        {
         "firstgid":188,
         "source":"..\/tilesets\/plants.json"
        }, 
        {
         "firstgid":252,
         "source":"..\/tilesets\/enemies.json"
        }, 
        {
         "firstgid":259,
         "source":"..\/tilesets\/stones.json"
        }, 
        {
         "firstgid":261,
         "source":"..\/tilesets\/powerups.json"
        }, 
        {
         "firstgid":268,
         "source":"..\/tilesets\/doors.json"
        }, 
        {
         "firstgid":274,
         "source":"..\/tilesets\/objects.json"
        }, 
        {
         "firstgid":275,
         "source":"..\/tilesets\/artifact.json"
        }],
 "tilewidth":8,
 "type":"map",
 "version":1.2,
 "width":150
}