{ "compressionlevel":-1,
 "height":28,
 "infinite":false,
 "layers":[
        {
         "compression":"zlib",
         "data":"eJzt2d9KwzAUx\/G8\/0Nsp97p8E691Kr4Fv6pE8FLYS9gCz0Yspw2bfYnG98PhGbp2a8HWsZCnQMAAAAAAADQWRjrN+249cbdSI4E47IdV\/08R5gb5ul1UnKu+5HbEw5HXPzey1bl\/NxFRp4Yc5Rt6fb\/XOXkiTFH+cT9P1\/+Wm6m\/zs1N0+MOconwbFj\/X+bmzk3bxXJxGnQeyeFZ+4y61yk7n+OaVl4puwwC1By7AZwllbjJQAmekqoedx7Fzg3a29+YdR8HqIRAEXQfbu+Zx17vwoAAE7Hs7FeZ2Tct+NhoH5oH5tz3aHzKfviruZlwvVT+1Ap+\/d6Qt4UtbGe0tMcX8Z6481\/jBrdg2pG1R\/f2\/ERqVP+PrYKjo1LF+u9Ms6n7Iu7mu+Eut+RPqqgD52v3bbXdrx5n5tIXsjP1u9vRuoaIyvWEwCU7g\/+6GL3",
         "encoding":"base64",
         "height":28,
         "id":1,
         "name":"Decorations",
         "opacity":1,
         "type":"tilelayer",
         "visible":true,
         "width":150,
         "x":0,
         "y":0
        }, 
        {
         "draworder":"topdown",
         "id":2,
         "name":"Powerups",
         "objects":[],
         "opacity":1,
         "type":"objectgroup",
         "visible":true,
         "x":0,
         "y":0
        }, 
        {
         "draworder":"topdown",
         "id":3,
         "name":"Enemies",
         "objects":[
                {
                 "gid":253,
                 "height":16,
                 "id":12,
                 "name":"",
                 "rotation":0,
                 "type":"",
                 "visible":true,
                 "width":16,
                 "x":448,
                 "y":208
                }, 
                {
                 "gid":254,
                 "height":40,
                 "id":25,
                 "name":"",
                 "rotation":0,
                 "type":"",
                 "visible":true,
                 "width":32,
                 "x":528,
                 "y":208
                }, 
                {
                 "gid":254,
                 "height":40,
                 "id":26,
                 "name":"",
                 "rotation":0,
                 "type":"",
                 "visible":true,
                 "width":32,
                 "x":168,
                 "y":208
                }, 
                {
                 "gid":256,
                 "height":36,
                 "id":28,
                 "name":"",
                 "rotation":0,
                 "type":"",
                 "visible":true,
                 "width":62,
                 "x":696,
                 "y":208
                }],
         "opacity":1,
         "type":"objectgroup",
         "visible":true,
         "x":0,
         "y":0
        }, 
        {
         "draworder":"topdown",
         "id":4,
         "name":"player",
         "objects":[
                {
                 "height":8,
                 "id":2,
                 "name":"",
                 "rotation":0,
                 "type":"",
                 "visible":true,
                 "width":8,
                 "x":-8,
                 "y":0
                }],
         "opacity":1,
         "type":"objectgroup",
         "visible":true,
         "x":0,
         "y":0
        }, 
        {
         "draworder":"topdown",
         "id":5,
         "name":"Special Blocks",
         "objects":[
                {
                 "gid":270,
                 "height":64,
                 "id":8,
                 "name":"",
                 "properties":[
                        {
                         "name":"dest",
                         "type":"string",
                         "value":"14.json"
                        }],
                 "rotation":0,
                 "type":"",
                 "visible":true,
                 "width":8,
                 "x":0,
                 "y":168
                }, 
                {
                 "gid":271,
                 "height":64,
                 "id":9,
                 "name":"",
                 "properties":[
                        {
                         "name":"dest",
                         "type":"string",
                         "value":"37.json"
                        }],
                 "rotation":0,
                 "type":"",
                 "visible":true,
                 "width":8,
                 "x":1192,
                 "y":216
                }],
         "opacity":1,
         "type":"objectgroup",
         "visible":true,
         "x":0,
         "y":0
        }, 
        {
         "compression":"zlib",
         "data":"eJztwYEAAAAAw6D5U9\/gBFUBAAAAAAAAAAAAAAAAAAAA8AxBoAAB",
         "encoding":"base64",
         "height":28,
         "id":6,
         "name":"fake_tile",
         "opacity":1,
         "type":"tilelayer",
         "visible":true,
         "width":150,
         "x":0,
         "y":0
        }, 
        {
         "compression":"zlib",
         "data":"eJztm2mO3DYQRim1ZqwlPkxyidnnf5ZfSQzk\/idIC+aDH79Rxz3OtGMHIkBITbGKrGKxNrIPpZThWJdjner7+jwca1ff12+92tc+c20f9eT7XGFH4V6Ee6x9Bj3Bwxz6+rurT+YDzKH2YY59\/dbV2tc+zO2gPrPw0+65Q6PnAB+A8e9J9IJrqrigtxN+xh81DjgZcwzYMd6ho1OFj4yzxDfPnTWYBDeUll+DeJi\/4eUkHJ1wH0orSx4LflnGwG3eDjG25ZK1n0tLb86j11iGMd3wHdrm0q4FuOARawveg\/CxvrmfLAvGx9wN6\/WFZmixzMyllQto9\/5j\/5g\/i3DkGjOW18T7jLWHZuoWz0fBgJdx2Sdzafeh5WMorVx43UzjqLG8rktp+er1hU9ef6p1Gr\/NX\/M1dZ\/7eu78ZgzotXyxX1MOwG8ZokILeODrIFjrHebpOXm\/eX9b3zPfXF9ohm7m0wfMWF7u26m85IX1H\/y2Xu5Lu2eQO3TqEGPSBn+gyfKOTFBNh+2Z96\/3kmXN+os1pA1Zh85RY0ILOIbS7lvLNf2gp9c3nugHz8dycQh8npttLfO0jqe\/5SV55Dma35Nwet09pvVd0tCVVuYM6zVP3TptjIeesa3shd\/8Nx9yze0jWK+bDvsJ7IFFsN5L1r32d7wmXr9ZbeYR363jmMdB49smpW2Ef9aHKUfWQ16DfuPdY1s\/Jk+992wPl\/hmuehiLMtr6lXzjbVgH6UtnqKav7b\/s34ju5Yp2xDP0zbW\/qllIv0Ny9gpeMaxnt2as\/WHbT1zTn970TtzWgIudUv6OJav3IfIqW2Y98NQWvqsD7Zo6Eu799zWl5YuaElfJv0K7yPmnf6EZaIrL2VkimfGK9Zf6R+Z5owbLN\/2981H+6mnaJ9LK3tzVNa3C7z25+x32QZbL1oubNMcf3ndzCvLQR9t9ncsw94jlmv7C6PGsL9t+jKWtY11zGVcuUcsU7ark8a0jCNLxuu40PY1fRXLm3VRV9q1YkzH1KY59+4\/xSPwwHZuULUu7WIM8xM6H4\/1+VifjvWhjvlQ2x7r+1S\/05e2B7XznKPvo\/o5FrSPOKkf9VHtT\/r+WGGZx3NpcydT4BsFPwoucTJ3xwZPwvFQWlq8tsA4ljnl36XfaL\/Fe9E61vsCXLnXO+HK\/AHyMJVWdrrS6gPba\/sNGWc5LrZNY5\/8VV6WHzbatsqpfu\/PhP9aY7w\/8f6asgX3S3lp19Iu2Se2LM0Bi\/61rzRGX9tjxwLWg47tgB3V3zJlW+09aR\/D9sN+r\/excwNr+5ZM7eV15bfS2nDz1\/Z4yx5mbJg+iuUuYU\/FlMZBH8fp6L1B+NPu2iew\/2V77Dhw0fPDv2PnXlRW2Urfzf6M8xj2i+2vpG\/k+Nbx4hxw9rm2fgMzalzLsf1n55AOaltKa+8yBkIH7jL19uXX8mn9Msebvo7zmayVZcl5HdsuxzuOLVh7+4V94BwE6xyFfcTMV9tvc+yFnbXvvsvU5Qo2MXMO9rXT5tgvT9\/HPtJW\/Oc4zjJi3eO43vbRuTePPVdaHJ896N000b7L1OXLz6X11W2frAssW47BnMuwH+aY0fkm5\/zsR9sf70urgxznWd6BPae8ZWy2l\/PKqrfQD\/Z7t94z75J2MPN+9sVsdw3veDJzU7aHts3Wi3v5dsvqb9kG2Tb6zAQ9YjtnmXP853bD2Wb6\/ANc7mcbajvrnMNevu2y2kT7UOgcdI1tmXML48bvPFcxnjyLSHzWm5ljz7PAXV99HwW95VjeZ15pm7B1zrPa10\/5TLnNMyfHgMig8xVd4Bwvw4a9XKCQl89z+Mwn+DzbuifP6KyD7G\/3pY37nFt1bsMxRPp35\/rta\/nxdWzYywXKKltbZ6a+F+DzYc5EH+L9Od755r7kBp5Kewbq886n0p7Dgotyf6w3x3pbn6vMXUVd53l3rL+\/CYf2culyqRj+3HPfvEeV+XbbaPy+P996snv53xXfrbEt9VmnY09k74\/\/YrJ7+W4KPp7PpX1vx7ky5\/rXtt0m7uVUwd\/L+ze+d5Mxgu9V7DZxL1vFsabvXFlHTfHdZwWrbL213jo39qTfT288\/qlxPtdG+dL5fC16PNaXls\/N0WeWvk\/u82nfufE351PelY\/x4vr0eQP5vNv6\/aY+b2u9Lh\/jzbm+3wj2tnyyz\/QfNc6k\/vS90nhTxflOlZiXeVzXim+ZZyb3Fd9Nhb+ucFPFdV\/rtfABNwUcPIBu5kAsTv9Zc8XPBWauuBfRRsyODTFv72Lcu1qJ+SfBw3fouNJz0e+7Og7vrP19fa4FWWL9fUfV54\/Yx62z9IT1vX7n0py7y3tn9tt8F2zSu2OL\/K+Az\/7zfpzHcK7Y+8a55NxXk8Z1nOxveQ6LbresZu4y7yeZ784xGk\/aC\/PMd0LNJ98LzDsv\/s+G7yz7PoR97VxPnxOCY33\/G5shalU=",
         "encoding":"base64",
         "height":28,
         "id":7,
         "name":"Tile Layer 1",
         "opacity":1,
         "type":"tilelayer",
         "visible":true,
         "width":150,
         "x":0,
         "y":0
        }, 
        {
         "color":"#000000",
         "draworder":"topdown",
         "id":8,
         "name":"solid",
         "objects":[
                {
                 "height":64,
                 "id":16,
                 "name":"",
                 "rotation":0,
                 "type":"",
                 "visible":true,
                 "width":1200,
                 "x":0,
                 "y":0
                }, 
                {
                 "height":96,
                 "id":17,
                 "name":"",
                 "rotation":0,
                 "type":"",
                 "visible":true,
                 "width":336,
                 "x":864,
                 "y":64
                }, 
                {
                 "height":48,
                 "id":18,
                 "name":"",
                 "rotation":0,
                 "type":"",
                 "visible":true,
                 "width":96,
                 "x":0,
                 "y":64
                }, 
                {
                 "height":64,
                 "id":19,
                 "name":"",
                 "rotation":0,
                 "type":"",
                 "visible":true,
                 "width":96,
                 "x":0,
                 "y":160
                }, 
                {
                 "height":16,
                 "id":20,
                 "name":"",
                 "rotation":0,
                 "type":"",
                 "visible":true,
                 "width":1104,
                 "x":96,
                 "y":208
                }],
         "opacity":1,
         "type":"objectgroup",
         "visible":true,
         "x":0,
         "y":0
        }, 
        {
         "draworder":"topdown",
         "id":9,
         "name":"Collision Objects",
         "objects":[
                {
                 "height":96,
                 "id":21,
                 "name":"",
                 "rotation":0,
                 "type":"slope_bottomleft",
                 "visible":true,
                 "width":96,
                 "x":768,
                 "y":64
                }, 
                {
                 "height":48,
                 "id":22,
                 "name":"",
                 "rotation":0,
                 "type":"slope_bottomright",
                 "visible":true,
                 "width":48,
                 "x":96,
                 "y":64
                }, 
                {
                 "height":48,
                 "id":23,
                 "name":"",
                 "rotation":0,
                 "type":"slope_topright",
                 "visible":true,
                 "width":48,
                 "x":96,
                 "y":160
                }],
         "opacity":1,
         "type":"objectgroup",
         "visible":true,
         "x":0,
         "y":0
        }, 
        {
         "draworder":"topdown",
         "id":10,
         "name":"Camera Guides",
         "objects":[],
         "opacity":1,
         "type":"objectgroup",
         "visible":true,
         "x":0,
         "y":0
        }, 
        {
         "draworder":"topdown",
         "id":11,
         "name":"Map Hints",
         "objects":[],
         "opacity":1,
         "type":"objectgroup",
         "visible":true,
         "x":0,
         "y":0
        }],
 "nextlayerid":12,
 "nextobjectid":29,
 "orientation":"orthogonal",
 "properties":[
        {
         "name":"bgname",
         "type":"string",
         "value":"iridia"
        }, 
        {
         "name":"music",
         "type":"string",
         "value":"late_night_runaway.ogg"
        }],
 "renderorder":"right-down",
 "tiledversion":"1.3.4",
 "tileheight":8,
 "tilesets":[
        {
         "firstgid":1,
         "source":"..\/tilesets\/main_blue.json"
        }, 
        {
         "firstgid":111,
         "source":"..\/tilesets\/extras.json"
        }, 
        {
         "firstgid":188,
         "source":"..\/tilesets\/plants.json"
        }, 
        {
         "firstgid":252,
         "source":"..\/tilesets\/enemies.json"
        }, 
        {
         "firstgid":259,
         "source":"..\/tilesets\/stones.json"
        }, 
        {
         "firstgid":261,
         "source":"..\/tilesets\/powerups.json"
        }, 
        {
         "firstgid":268,
         "source":"..\/tilesets\/doors.json"
        }, 
        {
         "firstgid":274,
         "source":"..\/tilesets\/objects.json"
        }, 
        {
         "firstgid":275,
         "source":"..\/tilesets\/artifact.json"
        }],
 "tilewidth":8,
 "type":"map",
 "version":1.2,
 "width":150
}